[
  {
    "skillId": "skill_auth_setup",
    "keywords": ["auth", "login", "roles", "users", "rbac"]
  },
  {
    "skillId": "skill_crm_schema_design",
    "keywords": ["crm", "leads", "pipeline", "customers"]
  },
  {
    "skillId": "skill_quote_engine",
    "keywords": ["quote", "pricing", "proposal", "estimate"]
  },
  {
    "skillId": "skill_invoice_workflow",
    "keywords": ["invoice", "billing", "payments", "invoicing"]
  },
  {
    "skillId": "skill_admin_dashboard_builder",
    "keywords": ["dashboard", "admin", "analytics", "kpi"]
  }
]
